construct_classes/__init__.py
construct_classes/py.typed
construct_classes-0.2.2.dist-info/WHEEL
construct_classes-0.2.2.dist-info/METADATA
construct_classes-0.2.2.dist-info/RECORD
