Metadata-Version: 2.4
Name: construct-classes
Version: 0.2.2
Summary: Parse your binary structs into dataclasses
Author: matejcik
Author-email: matejcik <ja@matejcik.cz>
License-Expression: MIT
Classifier: Development Status :: 2 - Pre-Alpha
Classifier: Intended Audience :: Developers
Classifier: License :: OSI Approved :: MIT License
Classifier: Natural Language :: English
Classifier: Programming Language :: Python :: 3
Classifier: Programming Language :: Python :: 3.10
Classifier: Programming Language :: Python :: 3.11
Classifier: Programming Language :: Python :: 3.12
Classifier: Programming Language :: Python :: 3.13
Classifier: Programming Language :: Python :: 3.14
Requires-Dist: construct~=2.10
Requires-Python: >=3.10, <4.0
Project-URL: Homepage, https://github.com/matejcik/construct-classes
Project-URL: Repository, https://github.com/matejcik/construct-classes
